{"parsing_date": "2023-08-22", "uuid": "c4a15ea3-b525-5da9-a6a8-03beb1fe3fc2", "parent_uuid": "a7d2f427-66ba-476a-81cc-171a5d806b22", "companieshouse_id": "10388803", "name": "Djordje Djokovic", "full_name": "Djordje Djokovic", "linkedin_name": "Djordje Djokovic, PhD", "companieshouse_company_name": "Isize Limited", "occupations": ["Founder", "Shareholder"], "linkedin_url": "https://www.linkedin.com/in/djordje-djokovic-phd-683589", "country": "GB", "city": "", "experience": [{"items": [{"position": "Trader", "from": "2013-12-01", "to": "2021-10-01", "days": 2861, "country": "GB", "city": "London", "description": "Heading Automated Options Market Making"}], "organization": "Maven Securities", "from": "2013-12-01", "to": "2021-10-01", "days": 2861}, {"items": [{"position": "Co-Founder and Shareholder", "from": "2016-09-01", "to": "2021-03-01", "days": 1642, "country": "GB", "city": "London", "description": ""}], "organization": "iSIZE Technologies - Enhancing Video Streaming With Advanced Machine Learning", "from": "2016-09-01", "to": "2021-03-01", "days": 1642}, {"items": [{"position": "Quantitative Trader", "from": "2007-03-01", "to": "2013-07-01", "days": 2314, "country": "GB", "city": "London", "description": "Heading the implementation and trading of a profitable automated option market making business. Engineered and implemented a fully automated options market making system including:- Fully automated and stable volatility fitting solution- Intelligent option quote and hitting strategies- Advanced futures hedging strategies- Real time correlation between multiple products/ volatility surfaces- Currently simultaneously trading DAX and ESX index options on EUREX)Responsible for implementing high frequency infrastructure such as fast and efficient analytic libraries, economic tick data storage solutions and matching engine simulators for backtesting purposes.Managed global quantitative model implementations across global exchanges and our London, Chicago, Sydney and Hong Kong offices."}], "organization": "Liquid Capital Group", "from": "2007-03-01", "to": "2013-07-01", "days": 2314}, {"items": [{"position": "Algorithmic Trading Associate", "from": "2005-03-01", "to": "2007-12-01", "days": 1005, "country": "GB", "city": "London", "description": "Co-Developed automatic high frequency multi-asset trading platform including infrastructure and key pricing and order algorithms. The system was managing a daily trade frequency of around 5000 trades per day in more than 1000 securities (equity and fixed income).Trading and managing own high frequency equity book, monitoring trading platform performance and generating and implementing new algorithm ideas.Implemented backtesting engine,  strategy optimizer and responsible for development and testing of proprietary elements"}], "organization": "Dresdner Kleinwort", "from": "2005-03-01", "to": "2007-12-01", "days": 1005}], "education": [{"items": [{"degree": "PhD, Pricing of Real Options", "from": "2003-01-01", "to": "2010-01-01", "days": 2557, "country": "", "city": "", "description": "Pricing of patents and high technologies in uncertain markets using real option theory"}], "organization": "Cass Business School", "from": "2003-01-01", "to": "2010-01-01", "days": 2557}, {"items": [{"degree": "MSc Material Science, Nanotechnology", "from": "2002-01-01", "to": "2003-01-01", "days": 365, "country": "", "city": "", "description": ""}], "organization": "University of Hawaii at Manoa", "from": "2002-01-01", "to": "2003-01-01", "days": 365}, {"items": [{"degree": "Diplom Ingenieur, Mechanical Engineering", "from": "1996-01-01", "to": "2001-01-01", "days": 1827, "country": "", "city": "", "description": ""}], "organization": "RWTH Aachen University", "from": "1996-01-01", "to": "2001-01-01", "days": 1827}]}